{
  "metadata" : {
    "identifier" : "https://www.nettruyenio.com/truyen-tranh/mot-ngay-no-toi-bong-thanh-nang-cong-chua-241624",
    "title" : "Một Ngày Nọ Tôi Bỗng Thành Nàng Công Chúa - Chapter 110.5",
    "subtitle" : null,
    "author" : null,
    "narrator" : null,
    "language" : "vi",
    "description" : null,
    "publisher" : "N/A",
    "subject" : null,
    "modified" : null,
    "published" : "2023-06-24",
    "duration" : 0,
    "abridged" : false,
    "conformsTo" : "https://readium.org/webpub-manifest/profiles/divina",
    "numberOfPages" : 164,
    "readingProgression" : "ttb",
    "belongsTo" : null,
    "presentation" : {
      "fit" : "width",
      "overflow" : "scrolled",
      "continuous" : true
    },
    "@type" : null,
    "schema:license" : null
  },
  "links" : [ {
    "rel" : "self",
    "href" : "https://raw.githubusercontent.com/thuvienonline40/book_storage_collection/main/comic_manifest.json",
    "type" : "application/divina+json"
  } ],
  "readingOrder" : [ {
    "href" : "https://raw.githubusercontent.com/duyhuynh652018/comic_storage4/main/IMAGE/IMAGE_9f186057c1e175ab53b167179e553d76_adb7b74ba45926884a1eb7d2a5e3ec62_402897e16fe1b547b19514d1c834136c.jpg",
    "type" : "image/jpeg",
    "bitrate" : 0,
    "duration" : 0,
    "title" : null,
    "properties" : null,
    "alternate" : [ {
      "href" : "https://i338.ntcdntempv3.com/data/images/24161/775757/001.jpg?data=net",
      "type" : "image/jpeg",
      "bitrate" : 0,
      "duration" : 0,
      "title" : null,
      "properties" : null,
      "alternate" : null
    } ]
  }, {
    "href" : "https://raw.githubusercontent.com/duyhuynh652018/comic_storage4/main/IMAGE/IMAGE_9f186057c1e175ab53b167179e553d76_adb7b74ba45926884a1eb7d2a5e3ec62_10101e2213d9f5b2aae880aeb9134859.jpg",
    "type" : "image/jpeg",
    "bitrate" : 0,
    "duration" : 0,
    "title" : null,
    "properties" : null,
    "alternate" : [ {
      "href" : "https://i338.ntcdntempv3.com/data/images/24161/775757/002.jpg?data=net",
      "type" : "image/jpeg",
      "bitrate" : 0,
      "duration" : 0,
      "title" : null,
      "properties" : null,
      "alternate" : null
    } ]
  }, {
    "href" : "https://raw.githubusercontent.com/duyhuynh652018/comic_storage4/main/IMAGE/IMAGE_9f186057c1e175ab53b167179e553d76_adb7b74ba45926884a1eb7d2a5e3ec62_80374b32a91861efb27856eaaf0b1998.jpg",
    "type" : "image/jpeg",
    "bitrate" : 0,
    "duration" : 0,
    "title" : null,
    "properties" : null,
    "alternate" : [ {
      "href" : "https://i338.ntcdntempv3.com/data/images/24161/775757/003.jpg?data=net",
      "type" : "image/jpeg",
      "bitrate" : 0,
      "duration" : 0,
      "title" : null,
      "properties" : null,
      "alternate" : null
    } ]
  }, {
    "href" : "https://raw.githubusercontent.com/duyhuynh652018/comic_storage4/main/IMAGE/IMAGE_9f186057c1e175ab53b167179e553d76_adb7b74ba45926884a1eb7d2a5e3ec62_33b8090fda4faff1ab3c1ecb717abb36.jpg",
    "type" : "image/jpeg",
    "bitrate" : 0,
    "duration" : 0,
    "title" : null,
    "properties" : null,
    "alternate" : [ {
      "href" : "https://i338.ntcdntempv3.com/data/images/24161/775757/004.jpg?data=net",
      "type" : "image/jpeg",
      "bitrate" : 0,
      "duration" : 0,
      "title" : null,
      "properties" : null,
      "alternate" : null
    } ]
  }, {
    "href" : "https://raw.githubusercontent.com/duyhuynh652018/comic_storage4/main/IMAGE/IMAGE_9f186057c1e175ab53b167179e553d76_adb7b74ba45926884a1eb7d2a5e3ec62_38e4e09669f90483cc3947d3a67bc5fd.jpg",
    "type" : "image/jpeg",
    "bitrate" : 0,
    "duration" : 0,
    "title" : null,
    "properties" : null,
    "alternate" : [ {
      "href" : "https://i338.ntcdntempv3.com/data/images/24161/775757/005.jpg?data=net",
      "type" : "image/jpeg",
      "bitrate" : 0,
      "duration" : 0,
      "title" : null,
      "properties" : null,
      "alternate" : null
    } ]
  }, {
    "href" : "https://raw.githubusercontent.com/duyhuynh652018/comic_storage4/main/IMAGE/IMAGE_9f186057c1e175ab53b167179e553d76_adb7b74ba45926884a1eb7d2a5e3ec62_010e28382ba3e2c88569c1803aa3da64.jpg",
    "type" : "image/jpeg",
    "bitrate" : 0,
    "duration" : 0,
    "title" : null,
    "properties" : null,
    "alternate" : [ {
      "href" : "https://i338.ntcdntempv3.com/data/images/24161/775757/006.jpg?data=net",
      "type" : "image/jpeg",
      "bitrate" : 0,
      "duration" : 0,
      "title" : null,
      "properties" : null,
      "alternate" : null
    } ]
  }, {
    "href" : "https://raw.githubusercontent.com/duyhuynh652018/comic_storage4/main/IMAGE/IMAGE_9f186057c1e175ab53b167179e553d76_adb7b74ba45926884a1eb7d2a5e3ec62_d6d116e4836f29f6fa4be8f346117043.jpg",
    "type" : "image/jpeg",
    "bitrate" : 0,
    "duration" : 0,
    "title" : null,
    "properties" : null,
    "alternate" : [ {
      "href" : "https://i338.ntcdntempv3.com/data/images/24161/775757/007.jpg?data=net",
      "type" : "image/jpeg",
      "bitrate" : 0,
      "duration" : 0,
      "title" : null,
      "properties" : null,
      "alternate" : null
    } ]
  }, {
    "href" : "https://raw.githubusercontent.com/duyhuynh652018/comic_storage4/main/IMAGE/IMAGE_9f186057c1e175ab53b167179e553d76_adb7b74ba45926884a1eb7d2a5e3ec62_dc2f99e65227940fba1a8c8f4e0586d3.jpg",
    "type" : "image/jpeg",
    "bitrate" : 0,
    "duration" : 0,
    "title" : null,
    "properties" : null,
    "alternate" : [ {
      "href" : "https://i338.ntcdntempv3.com/data/images/24161/775757/008.jpg?data=net",
      "type" : "image/jpeg",
      "bitrate" : 0,
      "duration" : 0,
      "title" : null,
      "properties" : null,
      "alternate" : null
    } ]
  }, {
    "href" : "https://raw.githubusercontent.com/duyhuynh652018/comic_storage4/main/IMAGE/IMAGE_9f186057c1e175ab53b167179e553d76_adb7b74ba45926884a1eb7d2a5e3ec62_15c02a0c82c7f5d2285e27665cd6cde9.jpg",
    "type" : "image/jpeg",
    "bitrate" : 0,
    "duration" : 0,
    "title" : null,
    "properties" : null,
    "alternate" : [ {
      "href" : "https://i338.ntcdntempv3.com/data/images/24161/775757/009.jpg?data=net",
      "type" : "image/jpeg",
      "bitrate" : 0,
      "duration" : 0,
      "title" : null,
      "properties" : null,
      "alternate" : null
    } ]
  }, {
    "href" : "https://raw.githubusercontent.com/duyhuynh652018/comic_storage4/main/IMAGE/IMAGE_9f186057c1e175ab53b167179e553d76_adb7b74ba45926884a1eb7d2a5e3ec62_86d39e7c07ef9458ee15fe87fd6d0ffc.jpg",
    "type" : "image/jpeg",
    "bitrate" : 0,
    "duration" : 0,
    "title" : null,
    "properties" : null,
    "alternate" : [ {
      "href" : "https://i338.ntcdntempv3.com/data/images/24161/775757/010.jpg?data=net",
      "type" : "image/jpeg",
      "bitrate" : 0,
      "duration" : 0,
      "title" : null,
      "properties" : null,
      "alternate" : null
    } ]
  }, {
    "href" : "https://raw.githubusercontent.com/duyhuynh652018/comic_storage4/main/IMAGE/IMAGE_9f186057c1e175ab53b167179e553d76_adb7b74ba45926884a1eb7d2a5e3ec62_13ce855cabf9c0112f45a127b9e6097f.jpg",
    "type" : "image/jpeg",
    "bitrate" : 0,
    "duration" : 0,
    "title" : null,
    "properties" : null,
    "alternate" : [ {
      "href" : "https://i338.ntcdntempv3.com/data/images/24161/775757/011.jpg?data=net",
      "type" : "image/jpeg",
      "bitrate" : 0,
      "duration" : 0,
      "title" : null,
      "properties" : null,
      "alternate" : null
    } ]
  }, {
    "href" : "https://raw.githubusercontent.com/duyhuynh652018/comic_storage4/main/IMAGE/IMAGE_9f186057c1e175ab53b167179e553d76_adb7b74ba45926884a1eb7d2a5e3ec62_6819c495fad8bdb2fffd2f19ac98d717.jpg",
    "type" : "image/jpeg",
    "bitrate" : 0,
    "duration" : 0,
    "title" : null,
    "properties" : null,
    "alternate" : [ {
      "href" : "https://i338.ntcdntempv3.com/data/images/24161/775757/012.jpg?data=net",
      "type" : "image/jpeg",
      "bitrate" : 0,
      "duration" : 0,
      "title" : null,
      "properties" : null,
      "alternate" : null
    } ]
  }, {
    "href" : "https://raw.githubusercontent.com/duyhuynh652018/comic_storage4/main/IMAGE/IMAGE_9f186057c1e175ab53b167179e553d76_adb7b74ba45926884a1eb7d2a5e3ec62_4a534b2c8a7fa69f13a921b5b4b6b83b.jpg",
    "type" : "image/jpeg",
    "bitrate" : 0,
    "duration" : 0,
    "title" : null,
    "properties" : null,
    "alternate" : [ {
      "href" : "https://i338.ntcdntempv3.com/data/images/24161/775757/013.jpg?data=net",
      "type" : "image/jpeg",
      "bitrate" : 0,
      "duration" : 0,
      "title" : null,
      "properties" : null,
      "alternate" : null
    } ]
  }, {
    "href" : "https://raw.githubusercontent.com/duyhuynh652018/comic_storage4/main/IMAGE/IMAGE_9f186057c1e175ab53b167179e553d76_adb7b74ba45926884a1eb7d2a5e3ec62_9434d54f34512ae5dd8a835e7e1cc7ff.jpg",
    "type" : "image/jpeg",
    "bitrate" : 0,
    "duration" : 0,
    "title" : null,
    "properties" : null,
    "alternate" : [ {
      "href" : "https://i338.ntcdntempv3.com/data/images/24161/775757/014.jpg?data=net",
      "type" : "image/jpeg",
      "bitrate" : 0,
      "duration" : 0,
      "title" : null,
      "properties" : null,
      "alternate" : null
    } ]
  }, {
    "href" : "https://raw.githubusercontent.com/duyhuynh652018/comic_storage4/main/IMAGE/IMAGE_9f186057c1e175ab53b167179e553d76_adb7b74ba45926884a1eb7d2a5e3ec62_f125bfb71195531788dc8ee6dbe3a3fb.jpg",
    "type" : "image/jpeg",
    "bitrate" : 0,
    "duration" : 0,
    "title" : null,
    "properties" : null,
    "alternate" : [ {
      "href" : "https://i338.ntcdntempv3.com/data/images/24161/775757/015.jpg?data=net",
      "type" : "image/jpeg",
      "bitrate" : 0,
      "duration" : 0,
      "title" : null,
      "properties" : null,
      "alternate" : null
    } ]
  }, {
    "href" : "https://raw.githubusercontent.com/duyhuynh652018/comic_storage4/main/IMAGE/IMAGE_9f186057c1e175ab53b167179e553d76_adb7b74ba45926884a1eb7d2a5e3ec62_662061f7ed6d93054db42000896e3bcc.jpg",
    "type" : "image/jpeg",
    "bitrate" : 0,
    "duration" : 0,
    "title" : null,
    "properties" : null,
    "alternate" : [ {
      "href" : "https://i338.ntcdntempv3.com/data/images/24161/775757/016.jpg?data=net",
      "type" : "image/jpeg",
      "bitrate" : 0,
      "duration" : 0,
      "title" : null,
      "properties" : null,
      "alternate" : null
    } ]
  }, {
    "href" : "https://raw.githubusercontent.com/duyhuynh652018/comic_storage4/main/IMAGE/IMAGE_9f186057c1e175ab53b167179e553d76_adb7b74ba45926884a1eb7d2a5e3ec62_b342dd72ad413489cea98c1c9382b855.jpg",
    "type" : "image/jpeg",
    "bitrate" : 0,
    "duration" : 0,
    "title" : null,
    "properties" : null,
    "alternate" : [ {
      "href" : "https://i338.ntcdntempv3.com/data/images/24161/775757/017.jpg?data=net",
      "type" : "image/jpeg",
      "bitrate" : 0,
      "duration" : 0,
      "title" : null,
      "properties" : null,
      "alternate" : null
    } ]
  }, {
    "href" : "https://raw.githubusercontent.com/duyhuynh652018/comic_storage4/main/IMAGE/IMAGE_9f186057c1e175ab53b167179e553d76_adb7b74ba45926884a1eb7d2a5e3ec62_e568a50beb84067572dd102817ca7f38.jpg",
    "type" : "image/jpeg",
    "bitrate" : 0,
    "duration" : 0,
    "title" : null,
    "properties" : null,
    "alternate" : [ {
      "href" : "https://i338.ntcdntempv3.com/data/images/24161/775757/018.jpg?data=net",
      "type" : "image/jpeg",
      "bitrate" : 0,
      "duration" : 0,
      "title" : null,
      "properties" : null,
      "alternate" : null
    } ]
  }, {
    "href" : "https://raw.githubusercontent.com/duyhuynh652018/comic_storage4/main/IMAGE/IMAGE_9f186057c1e175ab53b167179e553d76_adb7b74ba45926884a1eb7d2a5e3ec62_d221a414ce586a700f0aa352a2a63672.jpg",
    "type" : "image/jpeg",
    "bitrate" : 0,
    "duration" : 0,
    "title" : null,
    "properties" : null,
    "alternate" : [ {
      "href" : "https://i338.ntcdntempv3.com/data/images/24161/775757/019.jpg?data=net",
      "type" : "image/jpeg",
      "bitrate" : 0,
      "duration" : 0,
      "title" : null,
      "properties" : null,
      "alternate" : null
    } ]
  }, {
    "href" : "https://raw.githubusercontent.com/duyhuynh652018/comic_storage4/main/IMAGE/IMAGE_9f186057c1e175ab53b167179e553d76_adb7b74ba45926884a1eb7d2a5e3ec62_b59c6811d1dfd306e1fee8ff8d383155.jpg",
    "type" : "image/jpeg",
    "bitrate" : 0,
    "duration" : 0,
    "title" : null,
    "properties" : null,
    "alternate" : [ {
      "href" : "https://i338.ntcdntempv3.com/data/images/24161/775757/020.jpg?data=net",
      "type" : "image/jpeg",
      "bitrate" : 0,
      "duration" : 0,
      "title" : null,
      "properties" : null,
      "alternate" : null
    } ]
  }, {
    "href" : "https://raw.githubusercontent.com/duyhuynh652018/comic_storage4/main/IMAGE/IMAGE_9f186057c1e175ab53b167179e553d76_adb7b74ba45926884a1eb7d2a5e3ec62_cf796aef1461ff3776d9735b9ae45f60.jpg",
    "type" : "image/jpeg",
    "bitrate" : 0,
    "duration" : 0,
    "title" : null,
    "properties" : null,
    "alternate" : [ {
      "href" : "https://i338.ntcdntempv3.com/data/images/24161/775757/021.jpg?data=net",
      "type" : "image/jpeg",
      "bitrate" : 0,
      "duration" : 0,
      "title" : null,
      "properties" : null,
      "alternate" : null
    } ]
  }, {
    "href" : "https://raw.githubusercontent.com/duyhuynh652018/comic_storage4/main/IMAGE/IMAGE_9f186057c1e175ab53b167179e553d76_adb7b74ba45926884a1eb7d2a5e3ec62_7cbbeda1755e5e1e22726570913750f4.jpg",
    "type" : "image/jpeg",
    "bitrate" : 0,
    "duration" : 0,
    "title" : null,
    "properties" : null,
    "alternate" : [ {
      "href" : "https://i338.ntcdntempv3.com/data/images/24161/775757/022.jpg?data=net",
      "type" : "image/jpeg",
      "bitrate" : 0,
      "duration" : 0,
      "title" : null,
      "properties" : null,
      "alternate" : null
    } ]
  }, {
    "href" : "https://raw.githubusercontent.com/duyhuynh652018/comic_storage4/main/IMAGE/IMAGE_9f186057c1e175ab53b167179e553d76_adb7b74ba45926884a1eb7d2a5e3ec62_ceb8be54f3fd7b6d39116521fbe6abaa.jpg",
    "type" : "image/jpeg",
    "bitrate" : 0,
    "duration" : 0,
    "title" : null,
    "properties" : null,
    "alternate" : [ {
      "href" : "https://i338.ntcdntempv3.com/data/images/24161/775757/023.jpg?data=net",
      "type" : "image/jpeg",
      "bitrate" : 0,
      "duration" : 0,
      "title" : null,
      "properties" : null,
      "alternate" : null
    } ]
  }, {
    "href" : "https://raw.githubusercontent.com/duyhuynh652018/comic_storage4/main/IMAGE/IMAGE_9f186057c1e175ab53b167179e553d76_adb7b74ba45926884a1eb7d2a5e3ec62_0117043102cb785b705dd1f358f66716.jpg",
    "type" : "image/jpeg",
    "bitrate" : 0,
    "duration" : 0,
    "title" : null,
    "properties" : null,
    "alternate" : [ {
      "href" : "https://i338.ntcdntempv3.com/data/images/24161/775757/024.jpg?data=net",
      "type" : "image/jpeg",
      "bitrate" : 0,
      "duration" : 0,
      "title" : null,
      "properties" : null,
      "alternate" : null
    } ]
  }, {
    "href" : "https://raw.githubusercontent.com/duyhuynh652018/comic_storage4/main/IMAGE/IMAGE_9f186057c1e175ab53b167179e553d76_adb7b74ba45926884a1eb7d2a5e3ec62_e423f46f5a0fd29127941e0fd3ed4a42.jpg",
    "type" : "image/jpeg",
    "bitrate" : 0,
    "duration" : 0,
    "title" : null,
    "properties" : null,
    "alternate" : [ {
      "href" : "https://i338.ntcdntempv3.com/data/images/24161/775757/025.jpg?data=net",
      "type" : "image/jpeg",
      "bitrate" : 0,
      "duration" : 0,
      "title" : null,
      "properties" : null,
      "alternate" : null
    } ]
  }, {
    "href" : "https://raw.githubusercontent.com/duyhuynh652018/comic_storage4/main/IMAGE/IMAGE_9f186057c1e175ab53b167179e553d76_adb7b74ba45926884a1eb7d2a5e3ec62_89bec3a20fd552c0d6c190ff747d19bb.jpg",
    "type" : "image/jpeg",
    "bitrate" : 0,
    "duration" : 0,
    "title" : null,
    "properties" : null,
    "alternate" : [ {
      "href" : "https://i338.ntcdntempv3.com/data/images/24161/775757/026.jpg?data=net",
      "type" : "image/jpeg",
      "bitrate" : 0,
      "duration" : 0,
      "title" : null,
      "properties" : null,
      "alternate" : null
    } ]
  }, {
    "href" : "https://raw.githubusercontent.com/duyhuynh652018/comic_storage4/main/IMAGE/IMAGE_9f186057c1e175ab53b167179e553d76_adb7b74ba45926884a1eb7d2a5e3ec62_9435fd71a2ce900cc2fe2f8b5458f0b5.jpg",
    "type" : "image/jpeg",
    "bitrate" : 0,
    "duration" : 0,
    "title" : null,
    "properties" : null,
    "alternate" : [ {
      "href" : "https://i338.ntcdntempv3.com/data/images/24161/775757/027.jpg?data=net",
      "type" : "image/jpeg",
      "bitrate" : 0,
      "duration" : 0,
      "title" : null,
      "properties" : null,
      "alternate" : null
    } ]
  }, {
    "href" : "https://raw.githubusercontent.com/duyhuynh652018/comic_storage4/main/IMAGE/IMAGE_9f186057c1e175ab53b167179e553d76_adb7b74ba45926884a1eb7d2a5e3ec62_a10243c14d638e29797d932091c11cf2.jpg",
    "type" : "image/jpeg",
    "bitrate" : 0,
    "duration" : 0,
    "title" : null,
    "properties" : null,
    "alternate" : [ {
      "href" : "https://i338.ntcdntempv3.com/data/images/24161/775757/028.jpg?data=net",
      "type" : "image/jpeg",
      "bitrate" : 0,
      "duration" : 0,
      "title" : null,
      "properties" : null,
      "alternate" : null
    } ]
  }, {
    "href" : "https://raw.githubusercontent.com/duyhuynh652018/comic_storage4/main/IMAGE/IMAGE_9f186057c1e175ab53b167179e553d76_adb7b74ba45926884a1eb7d2a5e3ec62_c075a7268ed11f057fc2ffef70bceb59.jpg",
    "type" : "image/jpeg",
    "bitrate" : 0,
    "duration" : 0,
    "title" : null,
    "properties" : null,
    "alternate" : [ {
      "href" : "https://i338.ntcdntempv3.com/data/images/24161/775757/029.jpg?data=net",
      "type" : "image/jpeg",
      "bitrate" : 0,
      "duration" : 0,
      "title" : null,
      "properties" : null,
      "alternate" : null
    } ]
  }, {
    "href" : "https://raw.githubusercontent.com/duyhuynh652018/comic_storage4/main/IMAGE/IMAGE_9f186057c1e175ab53b167179e553d76_adb7b74ba45926884a1eb7d2a5e3ec62_845e2e09c9ddb72c85cb1bf917fa88b8.jpg",
    "type" : "image/jpeg",
    "bitrate" : 0,
    "duration" : 0,
    "title" : null,
    "properties" : null,
    "alternate" : [ {
      "href" : "https://i338.ntcdntempv3.com/data/images/24161/775757/030.jpg?data=net",
      "type" : "image/jpeg",
      "bitrate" : 0,
      "duration" : 0,
      "title" : null,
      "properties" : null,
      "alternate" : null
    } ]
  }, {
    "href" : "https://raw.githubusercontent.com/duyhuynh652018/comic_storage4/main/IMAGE/IMAGE_9f186057c1e175ab53b167179e553d76_adb7b74ba45926884a1eb7d2a5e3ec62_2b4c7eeeb0f5c85be69d06dd8c697eb9.jpg",
    "type" : "image/jpeg",
    "bitrate" : 0,
    "duration" : 0,
    "title" : null,
    "properties" : null,
    "alternate" : [ {
      "href" : "https://i338.ntcdntempv3.com/data/images/24161/775757/031.jpg?data=net",
      "type" : "image/jpeg",
      "bitrate" : 0,
      "duration" : 0,
      "title" : null,
      "properties" : null,
      "alternate" : null
    } ]
  }, {
    "href" : "https://raw.githubusercontent.com/duyhuynh652018/comic_storage4/main/IMAGE/IMAGE_9f186057c1e175ab53b167179e553d76_adb7b74ba45926884a1eb7d2a5e3ec62_ac73160092ca31dd8db5f35102a483c5.jpg",
    "type" : "image/jpeg",
    "bitrate" : 0,
    "duration" : 0,
    "title" : null,
    "properties" : null,
    "alternate" : [ {
      "href" : "https://i338.ntcdntempv3.com/data/images/24161/775757/032.jpg?data=net",
      "type" : "image/jpeg",
      "bitrate" : 0,
      "duration" : 0,
      "title" : null,
      "properties" : null,
      "alternate" : null
    } ]
  }, {
    "href" : "https://raw.githubusercontent.com/duyhuynh652018/comic_storage4/main/IMAGE/IMAGE_9f186057c1e175ab53b167179e553d76_adb7b74ba45926884a1eb7d2a5e3ec62_1a9382daa98b3054c3e0fd0976a73b58.jpg",
    "type" : "image/jpeg",
    "bitrate" : 0,
    "duration" : 0,
    "title" : null,
    "properties" : null,
    "alternate" : [ {
      "href" : "https://i338.ntcdntempv3.com/data/images/24161/775757/033.jpg?data=net",
      "type" : "image/jpeg",
      "bitrate" : 0,
      "duration" : 0,
      "title" : null,
      "properties" : null,
      "alternate" : null
    } ]
  }, {
    "href" : "https://raw.githubusercontent.com/duyhuynh652018/comic_storage4/main/IMAGE/IMAGE_9f186057c1e175ab53b167179e553d76_adb7b74ba45926884a1eb7d2a5e3ec62_cb3b54ee73ee74d8c23b90b28a44f5fc.jpg",
    "type" : "image/jpeg",
    "bitrate" : 0,
    "duration" : 0,
    "title" : null,
    "properties" : null,
    "alternate" : [ {
      "href" : "https://i338.ntcdntempv3.com/data/images/24161/775757/034.jpg?data=net",
      "type" : "image/jpeg",
      "bitrate" : 0,
      "duration" : 0,
      "title" : null,
      "properties" : null,
      "alternate" : null
    } ]
  }, {
    "href" : "https://raw.githubusercontent.com/duyhuynh652018/comic_storage4/main/IMAGE/IMAGE_9f186057c1e175ab53b167179e553d76_adb7b74ba45926884a1eb7d2a5e3ec62_eb48434e24737ea5a3fda98bef1ce398.jpg",
    "type" : "image/jpeg",
    "bitrate" : 0,
    "duration" : 0,
    "title" : null,
    "properties" : null,
    "alternate" : [ {
      "href" : "https://i338.ntcdntempv3.com/data/images/24161/775757/035.jpg?data=net",
      "type" : "image/jpeg",
      "bitrate" : 0,
      "duration" : 0,
      "title" : null,
      "properties" : null,
      "alternate" : null
    } ]
  }, {
    "href" : "https://raw.githubusercontent.com/duyhuynh652018/comic_storage4/main/IMAGE/IMAGE_9f186057c1e175ab53b167179e553d76_adb7b74ba45926884a1eb7d2a5e3ec62_90834122bbc414001bb448528b309065.jpg",
    "type" : "image/jpeg",
    "bitrate" : 0,
    "duration" : 0,
    "title" : null,
    "properties" : null,
    "alternate" : [ {
      "href" : "https://i338.ntcdntempv3.com/data/images/24161/775757/036.jpg?data=net",
      "type" : "image/jpeg",
      "bitrate" : 0,
      "duration" : 0,
      "title" : null,
      "properties" : null,
      "alternate" : null
    } ]
  }, {
    "href" : "https://raw.githubusercontent.com/duyhuynh652018/comic_storage4/main/IMAGE/IMAGE_9f186057c1e175ab53b167179e553d76_adb7b74ba45926884a1eb7d2a5e3ec62_2e78c499d50ea6ff32ff8af1f6ebad23.jpg",
    "type" : "image/jpeg",
    "bitrate" : 0,
    "duration" : 0,
    "title" : null,
    "properties" : null,
    "alternate" : [ {
      "href" : "https://i338.ntcdntempv3.com/data/images/24161/775757/037.jpg?data=net",
      "type" : "image/jpeg",
      "bitrate" : 0,
      "duration" : 0,
      "title" : null,
      "properties" : null,
      "alternate" : null
    } ]
  } ],
  "toc" : null,
  "@context" : "https://readium.org/webpub-manifest/context.jsonld"
}